eksisozluk/EksiSozluk.py
eksisozluk/__init__.py
eksisozluk/Models/__init__.py
eksisozluk/Models/Auth/EksiToken.py
eksisozluk/Models/Auth/__init__.py
eksisozluk/Models/Entry/Entry.py
eksisozluk/Models/Entry/__init__.py
eksisozluk/Models/Exceptions/ClientException.py
eksisozluk/Models/Exceptions/EntryNotFoundException.py
eksisozluk/Models/Exceptions/TopicNotFoundException.py
eksisozluk/Models/Exceptions/UserNotFoundException.py
eksisozluk/Models/Exceptions/__init__.py
eksisozluk/Models/Index/Index.py
eksisozluk/Models/Index/IndexedTopic.py
eksisozluk/Models/Index/__init__.py
eksisozluk/Models/Responses/IndexResponse.py
eksisozluk/Models/Responses/LoginResponse.py
eksisozluk/Models/Responses/ResponseMessage.py
eksisozluk/Models/Responses/TopicResponse.py
eksisozluk/Models/Responses/UserEntriesResponse.py
eksisozluk/Models/Responses/UserResponse.py
eksisozluk/Models/Responses/__init__.py
eksisozluk/Models/Topic/Topic.py
eksisozluk/Models/Topic/Video.py
eksisozluk/Models/Topic/__init__.py
eksisozluk/Models/User/Badge.py
eksisozluk/Models/User/BadgeName.py
eksisozluk/Models/User/CursePeriod.py
eksisozluk/Models/User/EntryCounts.py
eksisozluk/Models/User/EntrySummary.py
eksisozluk/Models/User/Karma.py
eksisozluk/Models/User/KarmaName.py
eksisozluk/Models/User/PinnedEntryCounts.py
eksisozluk/Models/User/TopicID.py
eksisozluk/Models/User/TopicTitle.py
eksisozluk/Models/User/User.py
eksisozluk/Models/User/UserIdentifier.py
eksisozluk/Models/User/UserInfo.py
eksisozluk/Models/User/UserInfoEntryCounts.py
eksisozluk/Models/User/__init__.py
eksisozluk/tests/AnonClientTests.py
eksisozluk/tests/__init__.py
eksisozluk-1.0.6.dist-info/LICENSE
eksisozluk-1.0.6.dist-info/METADATA
eksisozluk-1.0.6.dist-info/WHEEL
eksisozluk-1.0.6.dist-info/top_level.txt
eksisozluk-1.0.6.dist-info/RECORD
