Metadata-Version: 2.1
Name: eksisozluk
Version: 1.0.6
Summary: Ekşisözlük API client
Home-page: https://github.com/e4c6/eksi_unofficial_api
Author: Mahir Tüzel
Author-email: e4c6@dataso.me
License: UNKNOWN
Project-URL: Bug Tracker, https://github.com/e4c6/eksi_unofficial_api/issues
Platform: UNKNOWN
Classifier: Programming Language :: Python :: 3
Classifier: License :: OSI Approved :: MIT License
Classifier: Operating System :: OS Independent
Requires-Python: >=3.6
License-File: LICENSE
Requires-Dist: requests
Requires-Dist: python-dateutil
